LASExplanation/LIMEBAG.py
LASExplanation/SHAP.py
LASExplanation/__init__.py
LASExplanation/camel-1.2.csv
LASExplanation/rq1.py
LASExplanation/rq2.py
LASExplanation/sk.py
LASExplanation/tests/__init__.py
LASExplanation/tests/testLIME.py
LASExplanation/tests/testSHAP.py
LASExplanation-0.0.1.dist-info/LICENSE
LASExplanation-0.0.1.dist-info/METADATA
LASExplanation-0.0.1.dist-info/WHEEL
LASExplanation-0.0.1.dist-info/top_level.txt
LASExplanation-0.0.1.dist-info/RECORD
